nle/version.py
nle/_pynethack.cpython-310-x86_64-linux-gnu.so
nle/libnethack.so
nle/_pyconverter.cpython-310-x86_64-linux-gnu.so
nle/__init__.py
nle/dataset/populate_db.py
nle/dataset/db.py
nle/dataset/dataset.py
nle/dataset/__init__.py
nle/scripts/read_tty.py
nle/scripts/ttyplay2.py
nle/scripts/ttyplay.py
nle/scripts/test_raw_nethack.py
nle/scripts/ttyrec.py
nle/scripts/check_nethack_speed.py
nle/scripts/collect_env.py
nle/scripts/play.py
nle/scripts/read_heaplog.py
nle/scripts/plot.py
nle/scripts/__init__.py
nle/tests/test_db.py
nle/tests/test_nethack.py
nle/tests/test_converter.py
nle/tests/test_profile.py
nle/tests/test_dataset.py
nle/tests/test_system.py
nle/tests/test_envs.py
nle/tests/test_populate_db.py
nle/nethack/actions.py
nle/nethack/nethack.py
nle/nethack/__init__.py
nle/env/tasks.py
nle/env/base.py
nle/env/__init__.py
nle/nethackdir/lev_comp
nle/nethackdir/dlb
nle/nethackdir/makedefs
nle/nethackdir/xlogfile
nle/nethackdir/recover
nle/nethackdir/perm
nle/nethackdir/nhdat
nle/nethackdir/dgn_comp
nle/nethackdir/logfile
nle/nethackdir/record
nle/nethackdir/man/recover.6
nle/nethackdir/man/makedefs.6
nle/nethackdir/man/lev_comp.6
nle/nethackdir/man/nethack.6
nle/nethackdir/man/dlb.6
nle/nethackdir/man/dgn_comp.6
nle/nethackdir/doc/lev_comp.txt
nle/nethackdir/doc/dgn_comp.txt
nle/nethackdir/doc/makedefs.txt
nle/nethackdir/doc/recover.txt
nle/nethackdir/doc/dlb.txt
nle/nethackdir/doc/nethack.txt
nle/nethackdir/dat/Tourist.des
nle/nethackdir/dat/Samurai.des
nle/nethackdir/dat/hh
nle/nethackdir/dat/tower.des
nle/nethackdir/dat/wizhelp
nle/nethackdir/dat/Arch.des
nle/nethackdir/dat/opthelp
nle/nethackdir/dat/Valkyrie.des
nle/nethackdir/dat/tribute
nle/nethackdir/dat/Knight.des
nle/nethackdir/dat/knox.des
nle/nethackdir/dat/oracle.des
nle/nethackdir/dat/symbols
nle/nethackdir/dat/endgame.des
nle/nethackdir/dat/Monk.des
nle/nethackdir/dat/oracles.txt
nle/nethackdir/dat/epitaph.txt
nle-1.2.0.dist-info/top_level.txt
nle-1.2.0.dist-info/METADATA
nle-1.2.0.dist-info/RECORD
nle-1.2.0.dist-info/entry_points.txt
nle-1.2.0.dist-info/WHEEL
nle-1.2.0.dist-info/licenses/LICENSE
